setup.py
kerax/__init__.py
kerax.egg-info/PKG-INFO
kerax.egg-info/SOURCES.txt
kerax.egg-info/dependency_links.txt
kerax.egg-info/requires.txt
kerax.egg-info/top_level.txt