Metadata-Version: 1.0
Name: kerax
Version: 0.0.0
Summary: kerax
Home-page: https://github.com/bojone/kerax
Author: bojone
Author-email: bojone@spaces.ac.cn
License: Apache License 2.0
Platform: UNKNOWN
